server.py
mcp_github_owners-0.2.0.dist-info/licenses/LICENSE
mcp_github_owners-0.2.0.dist-info/METADATA
mcp_github_owners-0.2.0.dist-info/WHEEL
mcp_github_owners-0.2.0.dist-info/entry_points.txt
mcp_github_owners-0.2.0.dist-info/top_level.txt
mcp_github_owners-0.2.0.dist-info/RECORD
