Metadata-Version: 2.4
Name: mcp-github-owners
Version: 0.2.0
Summary: Add your description here
Requires-Python: >=3.10
License-File: LICENSE
Requires-Dist: codeowners>=0.8.0
Requires-Dist: fastmcp>=2.3.3
Requires-Dist: python-decouple>=3.8
Requires-Dist: requests>=2.32.3
Dynamic: license-file
